<?xml version="1.0" encoding="UTF-8"?>
<openerp>
    <data>
        ##############################################################################
        #
        #    jasper_server module for OpenERP, 
        #    Copyright (C) 2009 SYLEAM Info Services ([http://www.syleam.fr/]) Christophe CHAUVET
        #
        #    This file is a part of jasper_server
        #
        #    jasper_server is free software: you can redistribute it and/or modify
        #    it under the terms of the GNU General Public License as published by
        #    the Free Software Foundation, either version 3 of the License, or
        #    (at your option) any later version.
        #
        #    jasper_server is distributed in the hope that it will be useful,
        #    but WITHOUT ANY WARRANTY; without even the implied warranty of
        #    MERCHANTABILITY or FITNESS FOR A PARTICULAR PURPOSE.  See the
        #    GNU General Public License for more details.
        #
        #    You should have received a copy of the GNU General Public License
        #    along with this program.  If not, see [http://www.gnu.org/licenses/].
        #
        ##############################################################################

        <menuitem id="menu_jasper"
            icon="STOCK_PRINT" 
            sequence="50" 
            name="Jasper Report" 
            parent="base.menu_custom"/>

        #
        # Jasper Server configuration
        #
        <record id="view_jasper_server_tree" model="ir.ui.view">
            <field name="name">jasper.server.tree</field>
            <field name="model">jasper.server</field>
            <field name="priority" eval="8"/>
            <field name="arch" type="xml">

                <tree string="Jasper Server">
                    <field name="sequence"/>
                    <field name="host"/>
                    <field name="port"/>
                    <field name="user"/>
                    <field name="prefix"/>
                    <field name="repo"/>
                </tree>

            </field>
        </record> 

        <record id="view_jasper_server_form" model="ir.ui.view">
            <field name="name">jasper.server.form</field>
            <field name="model">jasper.server</field>
            <field name="priority" eval="8"/>
            <field name="arch" type="xml">
                <form string="Jasper Server" version="7.0">
                    <header>
                        <button string="Check Auth" icon="gtk-ok" type="object" name="check_auth"/>
                    </header>
                    <sheet>
                        <div class="oe_title">
                            <div class="oe_edit_only">
                                <field name="enable" class="oe_inline"/>
                                <label string="Enable" for="enable"/>
                                <label for="host" string="Hostname or IP address"/>
                            </div>
                        </div>
                        <h1><field name="host" placeholder="eg: localhost or 127.0.0.1"/></h1>
                        <group colspan="4" col="6">
                            <group colspan="4" col="4">
                                <field name="port" placeholder="eg: 8080"/>
                                <field name="sequence"/>
                            </group>
                            <group colspan="2" col="2">
                                <field name="user" required="1" placeholder="By default user is jasperadmin"/>
                                <field name="pass" password="1" required="1" placeholder="By default the password is jasperadmin"/>
                            </group>
                        </group>
                        <group colspan="4" col="10">
                            <field name="prefix" colspan="10"/>
                            <field name="repo" colspan="10"/>
                        </group>
                        <group colspan="4">
                            <separator string="Check and Authentification status" colspan="4"/>
                            <field name="status" colspan="4" nolabel="1"/>
                        </group>
                    </sheet>
                </form>

            </field>
        </record>

        <record model="ir.actions.act_window" id="action_jasper_server">
            <field name="name">Jasper Server configuration</field>
            <field name="res_model">jasper.server</field>
            <field name="view_type">form</field>
            <field name="view_mode">tree,form</field>
            <field name="domain">[]</field>
            <field name="context">{}</field>
        </record>

        <menuitem id="menu_jasper_server"
            action="action_jasper_server"
            icon="STOCK_PREFERENCES"
            parent="menu_jasper"/>


    </data>
</openerp>
